bankid_asyncio/__init__.py
bankid_asyncio/clients/__init__.py
bankid_asyncio/clients/asynchronous.py
bankid_asyncio/clients/asynchronous_with_pydantic.py
bankid_asyncio/clients/bases.py
bankid_asyncio/clients/synchronous.py
bankid_asyncio/clients/synchronous_with_pydantic.py
bankid_asyncio/enums.py
bankid_asyncio/exceptions.py
bankid_asyncio/factory.py
bankid_asyncio/helpers.py
bankid_asyncio/interfaces.py
bankid_asyncio/messages.py
bankid_asyncio/schemas.py
bankid_asyncio-0.0.4.dist-info/LICENSE
bankid_asyncio-0.0.4.dist-info/WHEEL
bankid_asyncio-0.0.4.dist-info/METADATA
bankid_asyncio-0.0.4.dist-info/RECORD
