Metadata-Version: 2.1
Name: bankid-asyncio
Version: 0.0.4
Summary: BankID client for Python with asyncio support.
Home-page: https://kostiantyn-salnykov.github.io/bankid_asyncio/
License: MIT
Keywords: bankid,client,asyncio,pydantic,httpx
Author: Kostiantyn Salnykov
Author-email: kostiantyn.salnykov@gmail.com
Maintainer: Kostiantyn Salnykov
Maintainer-email: kostiantyn.salnykov@gmail.com
Requires-Python: >=3.8,<4.0
Classifier: License :: OSI Approved :: MIT License
Classifier: Programming Language :: Python :: 3
Classifier: Programming Language :: Python :: 3.8
Classifier: Programming Language :: Python :: 3.9
Classifier: Programming Language :: Python :: 3.10
Classifier: Topic :: Software Development
Classifier: Topic :: Software Development :: Libraries
Classifier: Topic :: Software Development :: Libraries :: Python Modules
Requires-Dist: httpx (>=0.23.0,<0.24.0)
Requires-Dist: pydantic (>=1.9.2,<2.0.0)
Project-URL: Documentation, https://kostiantyn-salnykov.github.io/bankid_asyncio/
Project-URL: Discussions, https://github.com/Kostiantyn-Salnykov/bankid_asyncio/discussions
Project-URL: Issues, https://github.com/Kostiantyn-Salnykov/bankid_asyncio/issues
Project-URL: Repository, https://github.com/Kostiantyn-Salnykov/bankid_asyncio/
